{
	"instance" : {
		"numberOfChannels" : "MasashiUmezawa 6/11/2018 10:39",
		"kind" : "MasashiUmezawa 6/11/2018 11:09",
		"isUnsubscribe" : "MasashiUmezawa 6/11/2018 11:15",
		"kind:" : "MasashiUmezawa 6/11/2018 11:09",
		"numberOfChannels:" : "MasashiUmezawa 6/11/2018 10:39",
		"payload" : "MasashiUmezawa 6/11/2018 11:13",
		"channel:" : "MasashiUmezawa 6/11/2018 10:39",
		"isNormal" : "MasashiUmezawa 6/11/2018 11:19",
		"printOn:" : "MasashiUmezawa 6/11/2018 11:18",
		"payload:" : "MasashiUmezawa 6/11/2018 11:13",
		"isSubscribe" : "MasashiUmezawa 6/11/2018 11:13",
		"channel" : "MasashiUmezawa 6/11/2018 10:39"
	},
	"class" : {
		"fromRawMessageArray:" : "MasashiUmezawa 6/11/2018 11:12"
	}
}